dictionarpy/__init__.py
dictionarpy/box.py
dictionarpy/dictionarpy.py
dictionarpy/porter_stemmer.py
dictionarpy/utils.py
dictionarpy/data/dictionary.db
dictionarpy-2.6.1.dist-info/licenses/LICENSE.txt
dictionarpy-2.6.1.dist-info/METADATA
dictionarpy-2.6.1.dist-info/WHEEL
dictionarpy-2.6.1.dist-info/entry_points.txt
dictionarpy-2.6.1.dist-info/top_level.txt
dictionarpy-2.6.1.dist-info/RECORD
