Metadata-Version: 2.4
Name: dictionarpy
Version: 2.6.1
Summary: Offline dictionary in the terminal
Author-email: Emmet Weyman <emmetweyman@vt.edu>
License:                     GNU GENERAL PUBLIC LICENSE
Classifier: Programming Language :: Python :: 3
Classifier: Operating System :: POSIX :: Linux
Requires-Python: >=3.11
License-File: LICENSE.txt
Dynamic: license-file
